MANIFEST.in
README.rst
config-template.yaml
setup.py
metzoo/__init__.py
metzoo/reader/__init__.py
metzoo/reader/reader.py
metzoo_python_reader.egg-info/PKG-INFO
metzoo_python_reader.egg-info/SOURCES.txt
metzoo_python_reader.egg-info/dependency_links.txt
metzoo_python_reader.egg-info/entry_points.txt
metzoo_python_reader.egg-info/not-zip-safe
metzoo_python_reader.egg-info/requires.txt
metzoo_python_reader.egg-info/top_level.txt