Metadata-Version: 1.1
Name: metzoo-python-reader
Version: 0.0.17
Summary: Python Data Reader for Metzoo
Home-page: https://bitbucket.org/edrans/metzoo-python-reader
Author: Edrans
Author-email: info@edrans.com
License: MIT
Keywords: metzoo monitoring metric
Platform: UNKNOWN
Classifier: Development Status :: 4 - Beta
Classifier: License :: OSI Approved :: MIT License
Classifier: Programming Language :: Python :: 2.7
